gfuncpy/__init__.py
gfuncpy/finite_difference.py
gfuncpy/grid_function.py
gfuncpy-0.1.8.dist-info/METADATA
gfuncpy-0.1.8.dist-info/WHEEL
gfuncpy-0.1.8.dist-info/licenses/LICENSE
gfuncpy-0.1.8.dist-info/RECORD
