Metadata-Version: 2.4
Name: gfuncpy
Version: 0.1.8
Summary: 
License-File: LICENSE
Author: ScottChiuNYC
Author-email: scott.chiu@rutgers.edu
Requires-Python: >=3.12,<4.0
Classifier: Programming Language :: Python :: 3
Classifier: Programming Language :: Python :: 3.12
Classifier: Programming Language :: Python :: 3.13
Classifier: Programming Language :: Python :: 3.14
Requires-Dist: matplotlib (>=3.10.3,<4.0.0)
Requires-Dist: numpy (>=2.3.1,<3.0.0)
Requires-Dist: pydata-sphinx-theme (>=0.16.1,<0.17.0)
Requires-Dist: scipy (>=1.16.0,<2.0.0)
